idin/__init__.py
idin/api.py
idin/certificate.py
idin/service_id.py
idin/types.py
idin/xml.py
idin/xsd.py
idin/idx/__init__.py
idin/idx/base.py
idin/idx/directory_request.py
idin/idx/directory_response.py
idin/idx/error.py
idin/idx/status_request.py
idin/idx/status_response.py
idin/idx/transaction_request.py
idin/idx/transaction_response.py
idin/idx/utils.py
idin/saml2/__init__.py
idin/saml2/authn.py
idin/saml2/exceptions.py
idin/saml2/response.py
idin-0.2.0.dist-info/LICENSE
idin-0.2.0.dist-info/METADATA
idin-0.2.0.dist-info/WHEEL
idin-0.2.0.dist-info/top_level.txt
idin-0.2.0.dist-info/RECORD
