Metadata-Version: 2.1
Name: idin
Version: 0.2.0
Summary: IDIN Module
Home-page: https://github.com/labd/python-idin
Author: Lab Digital
Author-email: opensource@labdigital.nl
License: MIT
Platform: UNKNOWN
Classifier: Development Status :: 5 - Production/Stable
Classifier: Programming Language :: Python :: 3
Classifier: Programming Language :: Python :: 3.6
Classifier: Programming Language :: Python :: 3.7
Classifier: Programming Language :: Python :: 3.8
Classifier: Programming Language :: Python :: Implementation :: CPython
Classifier: Programming Language :: Python :: Implementation :: PyPy
Requires-Dist: attrs (>=18.0.0)
Requires-Dist: cached-property (>=1.5.0)
Requires-Dist: cryptography (>=2.8)
Requires-Dist: lxml (>3.0)
Requires-Dist: pytz
Requires-Dist: python-dateutil (>=2.0.0)
Requires-Dist: requests (>=2.22.0)
Requires-Dist: pytz (>=2019.3)
Requires-Dist: xmlsec (>=1.3.0)
Provides-Extra: docs
Provides-Extra: test
Requires-Dist: freezegun (==0.3.15) ; extra == 'test'
Requires-Dist: requests-mock (==1.8.0) ; extra == 'test'
Requires-Dist: pytest-cov (==2.8.1) ; extra == 'test'
Requires-Dist: pytest (>=6.0.0rc1) ; extra == 'test'
Requires-Dist: coverage[toml] (==5.2) ; extra == 'test'
Requires-Dist: isort (==4.2.5) ; extra == 'test'
Requires-Dist: flake8 (==3.8.3) ; extra == 'test'
Requires-Dist: flake8-blind-except (==0.1.1) ; extra == 'test'
Requires-Dist: flake8-debugger (==1.4.0) ; extra == 'test'
Requires-Dist: flake8-imports ; extra == 'test'
